rasterstats/__init__.py
rasterstats/_version.py
rasterstats/cli.py
rasterstats/io.py
rasterstats/main.py
rasterstats/point.py
rasterstats/utils.py
rasterstats-0.20.0.dist-info/LICENSE.txt
rasterstats-0.20.0.dist-info/METADATA
rasterstats-0.20.0.dist-info/WHEEL
rasterstats-0.20.0.dist-info/entry_points.txt
rasterstats-0.20.0.dist-info/top_level.txt
rasterstats-0.20.0.dist-info/RECORD
